wheel_version.py
wheel_version-1.0.0.dist-info/METADATA
wheel_version-1.0.0.dist-info/WHEEL
wheel_version-1.0.0.dist-info/entry_points.txt
wheel_version-1.0.0.dist-info/RECORD
