Metadata-Version: 2.4
Name: wheel-version
Version: 1.0.0
Summary: Get the version of a wheel file
Project-URL: Repository, https://github.com/zeevro/wheel-version
Author-email: Zeev Rotshtein <zeevro@gmail.com>
License: CC0
Requires-Python: >=3.9
Requires-Dist: packaging
